central_error_codes/__init__.py
central_error_codes/error_code_pywrapper.py
central_error_codes/errors/cms-gw-error.json
central_error_codes/errors/error-codes.json
central_error_codes/errors/generic-error.json
central_error_codes/errors/llm-gw-error.json
central_error_codes/errors/recommendation-tool-error.json
central_error_codes/errors/review-tool-error.json
central_error_codes-1.5.1.dist-info/LICENSE
central_error_codes-1.5.1.dist-info/METADATA
central_error_codes-1.5.1.dist-info/WHEEL
central_error_codes-1.5.1.dist-info/top_level.txt
central_error_codes-1.5.1.dist-info/RECORD
