Metadata-Version: 2.2
Name: central_error_codes
Version: 1.5.1
Summary: A Python package to manage error codes for multiple microservices
Home-page: https://github.com/yourusername/central-error-codes
Author: Your Name
Author-email: your.email@example.com
Classifier: Programming Language :: Python :: 3
Classifier: License :: OSI Approved :: MIT License
Classifier: Operating System :: OS Independent
License-File: LICENSE
Dynamic: author
Dynamic: author-email
Dynamic: classifier
Dynamic: description
Dynamic: description-content-type
Dynamic: home-page
Dynamic: summary
